hypercrystal/__init__.py
hypercrystal/notation.py
hypercrystal/h2_math/__init__.py
hypercrystal/h2_math/h2_ray.py
hypercrystal/h2_math/h2_transform.py
hypercrystal/h2_math/h2_vector.py
hypercrystal/h2_math/high_functions.py
hypercrystal/h2_math/low_functions.py
hypercrystal/h2_math/matrix3D.py
hypercrystal/misc/__init__.py
hypercrystal/misc/h2_billboard.py
hypercrystal/misc/h2_camera.py
hypercrystal/misc/h2_lookup.py
hypercrystal/misc/h2_walker.py
hypercrystal/projections/__init__.py
hypercrystal/projections/gans.py
hypercrystal/projections/general_perspective.py
hypercrystal/projections/h2_projection.py
hypercrystal/projections/hyperbolical.py
hypercrystal/projections/hyperpolar.py
hypercrystal/projections/klein.py
hypercrystal/projections/pointcare.py
hypercrystal/shapes/__init__.py
hypercrystal/shapes/arc.py
hypercrystal/shapes/circle.py
hypercrystal/shapes/horocycle.py
hypercrystal/shapes/hypercycle.py
hypercrystal/shapes/line.py
hypercrystal/shapes/polygon.py
hypercrystal/shapes/projected.py
hypercrystal/tessellations/__init__.py
hypercrystal/tessellations/flood_tessellation.py
hypercrystal/tessellations/tessellation_base.py
hypercrystal/tessellations/tiles/flood_tile.py
hypercrystal/tessellations/tiles/tile_base.py
hypercrystal-0.1.3.dist-info/METADATA
hypercrystal-0.1.3.dist-info/WHEEL
hypercrystal-0.1.3.dist-info/RECORD
