Metadata-Version: 2.4
Name: Hypercrystal
Version: 0.1.3
Summary: Python framework for realtime hyperbolic rendering in H2, build as a layer above pygame-ce.
Project-URL: Author, https://www.youtube.com/@tucan7112
Project-URL: Github, https://github.com/Tucan444/Hypercrystal
Author: Nix
License: MIT License
Classifier: Intended Audience :: Developers
Classifier: License :: OSI Approved :: MIT License
Classifier: Programming Language :: Python
Requires-Python: >=3.12
Requires-Dist: pygame-ce
